<?xml version="1.0" encoding="UTF-8"?>
<document xmlns="http://www.rbs.fr/schema/change-document/1.0" xmlns:xsi="http://www.w3.org/2001/XMLSchema-instance" xsi:schemaLocation="http://www.rbs.fr/schema/change-document/1.0 http://www.rbschange.fr/static/schema/change-document/4.0.xsd" model-version="1.0" icon="photo" indexable="true" has-url="false" publish-on-day-change="true">
  <properties>
    <property name="summary" type="LongString" localized="true" indexed="description"/>
    <property name="media" type="modules_media/media" min-occurs="1" cascade-delete="true"/>
    <property name="thumbnail" type="modules_media/media" cascade-delete="true"/>
    <property name="mediahd" type="modules_media/media" cascade-delete="true"/>
    <property name="copyright" type="LongString" localized="true" indexed="description"/>
    <property name="startpublicationdate" localized="true"/>
    <property name="endpublicationdate" localized="true"/>
  </properties>
  <statuses default="DRAFT"/>
</document>
